{
  "generatedDate": "2026-06-22",
  "regions": {
    "10": {
      "generatedAt": "2026-06-22T23:23:30.346Z",
      "predictions": [
        {
          "id": "pred-10-1",
          "type": "weather",
          "summary": "Ulan sa CDO",
          "detail": "Magkaroon ng mga pag-ulan sa Cagayan de Oro sa susunod na linggo, dahil sa habagat. Inaasahan ang 2-3 araw na ulan, na may kasamang mga pagkidlat at kulog. Maghanda sa mga pagbabaha sa mga lugar na malapit sa Iponan River, at magdala ng payong o raincoat sa mga susunod na araw.",
          "confidenceLevel": "medium",
          "validUntil": "2026-06-29T23:23:30.346Z",
          "createdAt": "2026-06-22T23:23:30.346Z"
        },
        {
          "id": "pred-10-2",
          "type": "food",
          "summary": "Mura ng seafood",
          "detail": "Ang presyo ng seafood sa mga palengke ng Cagayan de Oro at Iligan ay inaasahang magpapatong sa P150-P200 kada kilo sa susunod na buwan, dahil sa mainit na panahon. Magandang bumili ng mga isda at iba pang seafood sa mga lugar na ito, at maghanda sa mga pagluluto ng mga masasarap na pagkaing-dagat.",
          "confidenceLevel": "high",
          "validUntil": "2026-07-22T23:23:30.346Z",
          "createdAt": "2026-06-22T23:23:30.346Z"
        },
        {
          "id": "pred-10-3",
          "type": "transport",
          "summary": "Trisikad fare up",
          "detail": "Ang pamasahe ng trisikad sa Butuan ay inaasahang tataas sa P10-P15 sa susunod na linggo, dahil sa pagtaas ng presyo ng gasolina. Maghanda sa mga pagbabago sa mga ruta ng trisikad at mag-isip ng mga alternatibong paraan ng transportasyon, tulad ng paglalakad o paggamit ng bisikleta.",
          "confidenceLevel": "low",
          "validUntil": "2026-07-06T23:23:30.346Z",
          "createdAt": "2026-06-22T23:23:30.346Z"
        }
      ]
    },
    "11": {
      "generatedAt": "2026-06-22T23:23:37.354Z",
      "predictions": [
        {
          "id": "pred-11-1",
          "type": "weather",
          "summary": "Uulan sa Tagum",
          "detail": "Sa susunod na 2 araw, inaasahan ang malakas na ulan sa Tagum, Davao del Norte, dahil sa low pressure area. Magdala ng payong o raincoat sa paglabas, at asikasuhin ang mga flood-prone area. Mag-prepare rin para sa posibleng brownout sa Digos.",
          "confidenceLevel": "medium",
          "validUntil": "2026-06-24T23:23:37.354Z",
          "createdAt": "2026-06-22T23:23:37.354Z"
        },
        {
          "id": "pred-11-2",
          "type": "food",
          "summary": "Mura na durian",
          "detail": "Sa ngayon, ang presyo ng durian sa Roxas Night Market ay bumaba sa P50-P70 kada kilo, dahil sa mainit na panahon. Mag-avail ng murang presyo at bilhin ang mga durian para sa mga susunod na araw. Pwede ring mag-try ng dragon fruit na mura rin sa Davao City.",
          "confidenceLevel": "high",
          "validUntil": "2026-06-24T23:23:37.354Z",
          "createdAt": "2026-06-22T23:23:37.354Z"
        },
        {
          "id": "pred-11-3",
          "type": "transport",
          "summary": "Habal-habal fare tataas",
          "detail": "Sa susunod na linggo, inaasahan ang pagtaas ng habal-habal fare sa Davao City, dahil sa pagtaas ng fuel price. Mag-prepare ng P10-P20 dagdag sa pamasahe, at mag-isip ng mga alternatibong transportasyon tulad ng jeepney o pag-walk. Pwede ring mag-plan ng mga itinerary para sa mga susunod na araw.",
          "confidenceLevel": "low",
          "validUntil": "2026-06-24T23:23:37.354Z",
          "createdAt": "2026-06-22T23:23:37.354Z"
        }
      ]
    },
    "13": {
      "generatedAt": "2026-06-22T23:23:45.137Z",
      "predictions": [
        {
          "id": "pred-13-1",
          "type": "fuel",
          "summary": "P2.50/liter pagtaas",
          "detail": "Sa susunod na linggo, asahan ang pagtaas ng presyo ng gasolina sa Metro Manila, lalo na sa mga gas station sa EDSA at Commonwealth Avenue, na aabot sa P2.50/liter. Ito ay dahil sa pagtaas ng global demand at mga hamon sa supply chain. Mag-ipon na ng budget para sa mga biyahe sa susunod na linggo.",
          "confidenceLevel": "high",
          "validUntil": "2026-06-29T23:23:45.137Z",
          "createdAt": "2026-06-22T23:23:45.137Z"
        },
        {
          "id": "pred-13-2",
          "type": "weather",
          "summary": "Ulan sa hapon",
          "detail": "Sa mga susunod na araw, asahan ang mga ulan sa hapon sa Metro Manila, lalo na sa mga lugar na malapit sa Marikina River at Pasig River. Ito ay dahil sa habagat na nagdudulot ng mga pag-ulan sa kalakhan ng Luzon. Magdala ng payong o raincoat para sa mga biyahe sa hapon.",
          "confidenceLevel": "medium",
          "validUntil": "2026-06-25T23:23:45.137Z",
          "createdAt": "2026-06-22T23:23:45.137Z"
        },
        {
          "id": "pred-13-3",
          "type": "transport",
          "summary": "P10/pasahero pagtaas",
          "detail": "Sa susunod na buwan, asahan ang pagtaas ng pamasahe sa MRT at LRT sa Metro Manila, na aabot sa P10/pasahero. Ito ay dahil sa pagtaas ng operating costs at mga hamon sa maintenance. Mag-isip ng mga paraan para magtipid sa pamasahe, tulad ng mag-commute sa maagang umaga o gumamit ng mga alternatibong ruta.",
          "confidenceLevel": "high",
          "validUntil": "2026-07-22T23:23:45.137Z",
          "createdAt": "2026-06-22T23:23:45.137Z"
        }
      ]
    },
    "04": {
      "generatedAt": "2026-06-22T23:23:53.519Z",
      "predictions": [
        {
          "id": "pred-04-1",
          "type": "fuel",
          "summary": "Bumaba gas price",
          "detail": "Sa mga susunod na linggo, asahan ang pagbaba ng presyo ng gasolina sa mga gas station sa CALABARZON, partikular sa Laguna at Batangas, dahil sa pagbaba ng demand. Ang presyo ng gasolina ay posibleng bumaba ng P2-P3 kada litro sa loob ng 2-3 linggo. Ito ay magandang pagkakataon para mag-refuel at mag-stock ng gasolina para sa mga factory workers at OFW families.",
          "confidenceLevel": "medium",
          "validUntil": "2026-07-06T23:23:53.519Z",
          "createdAt": "2026-06-22T23:23:53.519Z"
        },
        {
          "id": "pred-04-2",
          "type": "weather",
          "summary": "Ulan sa Cavite",
          "detail": "Sa mga susunod na araw, asahan ang pag-ulan sa Cavite at Rizal, dahil sa pagpasok ng habagat. Ang mga residente ay pinayuhan na magdala ng payong o raincoat sa mga susunod na 2-3 araw, lalo na sa mga nagtatrabaho sa labas. Ang ulan ay posibleng magdala ng baha sa mga mababang lugar, kaya't ang mga residente ay pinayuhan na maghanda at mag-evacuate kung kinakailangan.",
          "confidenceLevel": "high",
          "validUntil": "2026-06-25T23:23:53.519Z",
          "createdAt": "2026-06-22T23:23:53.519Z"
        },
        {
          "id": "pred-04-3",
          "type": "food",
          "summary": "Buko pie sale",
          "detail": "Sa mga susunod na linggo, asahan ang pagbaba ng presyo ng buko pie sa mga palengke sa Quezon, partikular sa Lucban, dahil sa pagdami ng supply ng buko. Ang presyo ng buko pie ay posibleng bumaba ng P20-P30 kada pie sa loob ng 2-3 linggo. Ito ay magandang pagkakataon para bumili ng buko pie at iba pang espesyal na produkto ng Quezon para sa mga OFW families at factory workers.",
          "confidenceLevel": "low",
          "validUntil": "2026-06-29T23:23:53.519Z",
          "createdAt": "2026-06-22T23:23:53.519Z"
        }
      ]
    },
    "03": {
      "generatedAt": "2026-06-21T23:20:06.088Z",
      "predictions": [
        {
          "id": "pred-03-1",
          "type": "weather",
          "summary": "Uulan sa Linggo",
          "detail": "Magkakaroon ng malakas na ulan sa mga susunod na araw sa Central Luzon, lalo na sa Pampanga at Tarlac, dahil sa habagat. Inaasahan ang 2-3 inches ng ulan sa loob ng 2 araw. Magdala ng payong o jacket para sa Linggo at Lunes.",
          "confidenceLevel": "high",
          "validUntil": "2026-06-23T23:20:06.088Z",
          "createdAt": "2026-06-21T23:20:06.088Z"
        },
        {
          "id": "pred-03-2",
          "type": "food",
          "summary": "Mura na Lechon",
          "detail": "Dahil sa mga selebrasyon ng Linggo, ang presyo ng lechon sa Pampanga ay magiging mas mura, umaabot sa P2,500-P3,000 para sa isang kilo. Magandang pagkakataon para bumili at mag-ipon para sa mga susunod na okasyon. Pwedeng i-save ang P500-P1,000 sa grocery bill kung maghahanda ng sariling lechon sa bahay.",
          "confidenceLevel": "medium",
          "validUntil": "2026-06-23T23:20:06.088Z",
          "createdAt": "2026-06-21T23:20:06.088Z"
        },
        {
          "id": "pred-03-3",
          "type": "transport",
          "summary": "Jeepney Fare Up",
          "detail": "Sa susunod na linggo, ang pamahalaan ay magpapatupad ng P1-P2 na pagtaas sa pamasahe ng jeepney sa Central Luzon, partikular sa mga ruta ng Pampanga at Bulacan. Mag-ipon ng P20-P50 para sa dagdag na gastos sa pamasahe at mag-plano ng maigi para sa mga biyahe sa Linggo.",
          "confidenceLevel": "low",
          "validUntil": "2026-06-23T23:20:06.088Z",
          "createdAt": "2026-06-21T23:20:06.088Z"
        }
      ]
    },
    "07": {
      "generatedAt": "2026-06-21T23:20:13.255Z",
      "predictions": [
        {
          "id": "pred-07-1",
          "type": "weather",
          "summary": "Ulan sa June 24",
          "detail": "Inaasahan ang ulan sa Cebu City at Lapu-Lapu sa June 24, dahil sa habagat. Magdala ng payong o raincoat pagpunta sa Carbon Market. Maghanda rin sa posibleng baha sa mga mababang lugar.",
          "confidenceLevel": "medium",
          "validUntil": "2026-06-24T23:20:13.255Z",
          "createdAt": "2026-06-21T23:20:13.255Z"
        },
        {
          "id": "pred-07-2",
          "type": "food",
          "summary": "Mura na isda",
          "detail": "Ang presyo ng fresh fish sa Carbon Market ay maaaring bumaba ng 10-15% sa mga susunod na linggo dahil sa peak season ng pangisda. Mag-stock ng isda para sa linggong ito at mag-avail ng mga murang presyo. Mag-budget ng P200-P300 para sa isang kilo ng isda.",
          "confidenceLevel": "high",
          "validUntil": "2026-06-28T23:20:13.255Z",
          "createdAt": "2026-06-21T23:20:13.255Z"
        },
        {
          "id": "pred-07-3",
          "type": "transport",
          "summary": "Taas ng pamasahe",
          "detail": "Inaasahan ang taas ng pamasahe sa V-hire at jeepney sa Cebu City sa mga susunod na linggo dahil sa taas ng presyo ng krudo. Mag-budget ng P10-P20 dagdag para sa pamasahe sa mga susunod na linggo. Mag-isip ng mga paraan para magtipid sa pamasahe, tulad ng mag-walk o mag-bike sa mga malapit na lugar.",
          "confidenceLevel": "medium",
          "validUntil": "2026-07-05T23:20:13.255Z",
          "createdAt": "2026-06-21T23:20:13.255Z"
        }
      ]
    },
    "06": {
      "generatedAt": "2026-06-21T23:20:18.496Z",
      "predictions": [
        {
          "id": "pred-06-1",
          "type": "weather",
          "summary": "Uulan sa June",
          "detail": "Inaasahan ng mga residente sa Western Visayas na magkaroon ng mga pag-ulan sa mga susunod na araw, lalo na sa Iloilo at Bacolod, kaya't mainam na magdala ng payong o raincoat. Ang pag-ulan na ito ay dulot ng habagat at inaasahang magtatagal hanggang sa katapusan ng June, kaya't mahalaga na maghanda at magpakita ng mga dokumento sa mga lokal na awtoridad. Magdadala ito ng mga 2-3 inches ng ulan sa loob ng 2-3 araw.",
          "confidenceLevel": "high",
          "validUntil": "2026-06-23T23:20:18.496Z",
          "createdAt": "2026-06-21T23:20:18.496Z"
        },
        {
          "id": "pred-06-2",
          "type": "food",
          "summary": "Mura na La Paz Batchoy",
          "detail": "Sa mga darating na linggo, inaasahan na magkakaroon ng mga murang presyo ng La Paz Batchoy sa mga lokal na restawran sa Iloilo, dahil sa mga benta ng mga supplier ng mga ingrediente. Ito ay magandang pagkakataon upang bumili ng mga murang La Paz Batchoy sa mga restawran sa Iloilo, lalo na sa mga lugar na malapit sa La Paz Market. Ang presyo ay inaasahang magiging Php 50-70 bawat tasa.",
          "confidenceLevel": "medium",
          "validUntil": "2026-06-23T23:20:18.496Z",
          "createdAt": "2026-06-21T23:20:18.496Z"
        },
        {
          "id": "pred-06-3",
          "type": "transport",
          "summary": "Tipid sa gas",
          "detail": "Sa darating na linggo, mainam na mag-gas up sa mga gasoline station sa Bacolod at Iloilo, dahil sa inaasahang pagbaba ng presyo ng krudo. Ito ay magandang pagkakataon upang magtipid sa gas, lalo na para sa mga nagco-commute sa mga lugar na malayo. Ang presyo ng gas ay inaasahang magiging Php 50-60 bawat litro, kaya't mainam na mag-gas up ng maaga.",
          "confidenceLevel": "low",
          "validUntil": "2026-06-23T23:20:18.496Z",
          "createdAt": "2026-06-21T23:20:18.496Z"
        }
      ]
    },
    "05": {
      "generatedAt": "2026-06-21T23:20:23.587Z",
      "predictions": [
        {
          "id": "pred-05-1",
          "type": "weather",
          "summary": "Ulan sa Sorsogon",
          "detail": "May ulan sa Sorsogon ngayong linggo dahil sa habagat, magdadala ng 2-3 inches ng ulan sa loob ng 2 araw. Inaasahan ang pagbaha sa mga mababang lugar, kaya maghanda ng mga gamit pang-emergency. Magdadala ng 1-2 araw na pagkain at tubig para sa mga posibleng evacuation.",
          "confidenceLevel": "high",
          "validUntil": "2026-06-23T23:20:23.587Z",
          "createdAt": "2026-06-21T23:20:23.587Z"
        },
        {
          "id": "pred-05-2",
          "type": "food",
          "summary": "Mura na laing",
          "detail": "Ang presyo ng laing sa Naga ay bumaba ng 10% dahil sa oversupply, kaya magandang bumili ngayon para sa linggong ito. Maghanda ng P50 para sa isang kilo ng laing at i-prepare para sa Bicol Express. May mga promo rin sa mga lokal na palengke sa Legazpi.",
          "confidenceLevel": "medium",
          "validUntil": "2026-06-23T23:20:23.587Z",
          "createdAt": "2026-06-21T23:20:23.587Z"
        },
        {
          "id": "pred-05-3",
          "type": "transport",
          "summary": "Jeepney fare down",
          "detail": "Ang pamahalaan ng Bicol Region ay nagdeklara ng 5% na pagbaba sa pamasahe ng jeepney, kaya magandang mag-commute ngayon. Maghanda ng P10 para sa isang ride at mag-enjoy sa mas mura na biyahe. May mga dagdag na ruta rin sa mga tricycle sa Sorsogon.",
          "confidenceLevel": "low",
          "validUntil": "2026-06-23T23:20:23.587Z",
          "createdAt": "2026-06-21T23:20:23.587Z"
        }
      ]
    },
    "01": {
      "generatedAt": "2026-06-22T23:24:16.134Z",
      "predictions": [
        {
          "id": "pred-01-1",
          "type": "weather",
          "summary": "Ulan sa June",
          "detail": "Inaasahan ang mga pag-ulan sa Ilocos Region sa mga susunod na linggo, lalo na sa mga bayan ng Ilocos Norte at Ilocos Sur. Maghanda sa mga pagbaha at landslides sa mga lugar na malapit sa mga ilog. Ang mga residente ay inaanyayahan na magdala ng mga payong at rain boots sa mga susunod na 2 linggo.",
          "confidenceLevel": "high",
          "validUntil": "2026-07-06T23:24:16.134Z",
          "createdAt": "2026-06-22T23:24:16.134Z"
        },
        {
          "id": "pred-01-2",
          "type": "food",
          "summary": "Mura na bagnet",
          "detail": "Ang presyo ng bagnet sa Ilocos Region ay inaasahang magpapatuloy na mababa, lalo na sa mga susunod na buwan. Ang mga residente ay makakakuha ng bagnet sa presyong Php 150-200 kada kilo. Maghanda na bumili ng mga bagnet sa mga lokal na palengke sa Pangasinan at La Union.",
          "confidenceLevel": "medium",
          "validUntil": "2026-07-22T23:24:16.134Z",
          "createdAt": "2026-06-22T23:24:16.134Z"
        },
        {
          "id": "pred-01-3",
          "type": "transport",
          "summary": "Tumaas na pamasahe",
          "detail": "Ang pamasahe sa mga tricycle at jeepney sa Ilocos Region ay inaasahang tataas ng Php 1-2 sa mga susunod na linggo, dahil sa pagtaas ng presyo ng gasolina. Ang mga residente ay inaanyayahan na mag-plano ng mga ruta at oras ng biyahe upang makaiwas sa mga taas-presyo. Maghanda na magdala ng mga karagdagang pera para sa pamasahe.",
          "confidenceLevel": "low",
          "validUntil": "2026-06-29T23:24:16.134Z",
          "createdAt": "2026-06-22T23:24:16.134Z"
        }
      ]
    },
    "00": {
      "generatedAt": "2026-06-18T23:49:20.487Z",
      "predictions": [
        {
          "id": "pred-00-1",
          "type": "fuel",
          "summary": "Bumaba presyo",
          "detail": "Sa mga susunod na linggo, asahan ang posibleng pagbaba ng presyo ng krudo sa Pilipinas dahil sa pagtaas ng global supply. Ito ay makakatulong sa mga drayber at kompanya ng transportasyon na makatipid sa gastos. Ang presyo ng gasolina ay maaaring bumaba ng P0.50 hanggang P1.00 sa susunod na 2-3 buwan.",
          "confidenceLevel": "medium",
          "validUntil": "2026-07-18T23:49:20.487Z",
          "createdAt": "2026-06-18T23:49:20.487Z"
        },
        {
          "id": "pred-00-2",
          "type": "weather",
          "summary": "Uulan sa Hulyo",
          "detail": "Sa buwan ng Hulyo, asahan ang mga malakas na ulan sa mga probinsya sa Luzon at Visayas. Ito ay dahil sa habagat na may dala ng mga low-pressure area. Ang mga residente ay pinayuhang maghanda sa mga posibleng baha at landslides, at mag-stock ng mga emergency supplies.",
          "confidenceLevel": "high",
          "validUntil": "2026-07-02T23:49:20.487Z",
          "createdAt": "2026-06-18T23:49:20.487Z"
        },
        {
          "id": "pred-00-3",
          "type": "food",
          "summary": "Tumaas presyo ng bigas",
          "detail": "Sa mga susunod na buwan, asahan ang posibleng pagtaas ng presyo ng bigas sa Pilipinas dahil sa kakulangan ng supply. Ito ay makakaapekto sa mga pamilyang umaasa sa bigas bilang pangunahing pagkain. Ang mga konsumer ay pinayuhang mag-stock ng bigas at mag-plano sa mga pagkain para sa mga susunod na buwan, at mag-budget ng P500 hanggang P1000 para sa bigas bawat buwan.",
          "confidenceLevel": "medium",
          "validUntil": "2026-08-17T23:49:20.487Z",
          "createdAt": "2026-06-18T23:49:20.487Z"
        }
      ]
    }
  }
}